{"cmdbmodels":[{"ComponentName":"CLOUDERA MANAGER ON SVSVACMEDATALAKEDNN01","state":"critical","Service Categories":"BIGDATA","Service Units":"PCS.ODP.SK.BD.OS","Systemparts":"[unassigned]","Environments":"Development","Component":"A12207697"},{"ComponentName":"CLOUDERA MANAGER ON SVSVACMEDATALAKEPNN01","state":"unknown","Service Categories":"BIGDATA","Service Units":"PCS.ODP.SK.BD.OS","Systemparts":"Application UEDH","Environments":"Production","Component":"A12207685"},{"ComponentName":"CLOUDERA MANAGER ON SVSVACMEDATALAKETNN01","state":"critical","Service Categories":"BIGDATA","Service Units":"PCS.ODP.SK.BD.OS","Systemparts":"Application UEDH","Environments":"Preprod","Component":"A12207728"},{"ComponentName":"EACME01","state":"ok","Service Categories":"ORACLE","Service Units":"MIS.INT.HU.TSA.DB.ORACLE","Systemparts":"Middleware Database Oracle","Environments":"Entwicklung","Component":"A11792998"},{"ComponentName":"HACME01","state":"ok","Service Categories":"ORACLE","Service Units":"MIS.INT.HU.TSA.DB.ORACLE","Systemparts":"Middleware Database Oracle","Environments":"Test","Component":"A11773901"},{"ComponentName":"IACME01","state":"ok","Service Categories":"ORACLE","Service Units":"MIS.INT.HU.TSA.DB.ORACLE","Systemparts":"Middleware Database Oracle","Environments":"Integration","Component":"A11786155"},{"ComponentName":"IACME02","state":"ok","Service Categories":"ORACLE","Service Units":"MIS.INT.HU.TSA.DB.ORACLE","Systemparts":"Middleware Database Oracle","Environments":"Integration2","Component":"A12210967"},{"ComponentName":"ACME HFIX ORACLE JAVA ON SVSVACMEACMEHAPP01","state":"ok","Service Categories":"APPLICATION","Service Units":"MIS.INT.HU.ALP.LIN.APP","Systemparts":"Middleware JAVA","Environments":"Release Test","Component":"A11854299"},{"ComponentName":"ACME PROD JAVA ON SVSVACMEACMEPAPP01","state":"ok","Service Categories":"APPLICATION","Service Units":"MIS.INT.HU.ALP.LIN.APP","Systemparts":"Middleware JAVA","Environments":"Production","Component":"A11854435"},{"ComponentName":"ACME PROD JAVA ON SVSVACMEACMEPAPP02","state":"ok","Service Categories":"APPLICATION","Service Units":"MIS.INT.HU.ALP.LIN.APP","Systemparts":"Middleware JAVA","Environments":"Production","Component":"A11960352"},{"ComponentName":"JBOSS ON SVSVACMECRMDAPP01","state":"ok","Service Categories":"APPLICATION","Service Units":"MIS.INT.HU.ALP.LIN.APP","Systemparts":"Middleware JBOSS","Environments":"Development","Component":"A11992205"},{"ComponentName":"JBOSS ON SVSVACMECRMDAPP02","state":"ok","Service Categories":"APPLICATION","Service Units":"MIS.INT.HU.ALP.LIN.APP","Systemparts":"Middleware JBOSS","Environments":"Development","Component":"A11992402"},{"ComponentName":"JBOSS ON SVSVACMECRMMONDB01","state":"ok","Service Categories":"APPLICATION","Service Units":"MIS.INT.HU.ALP.LIN.APP","Systemparts":"Middleware JBOSS","Environments":"Administration","Component":"A11992435"},{"ComponentName":"JBOSS ON SVSVACMECRMMONAAPP02","state":"ok","Service Categories":"APPLICATION","Service Units":"MIS.INT.HU.ALP.LIN.APP","Systemparts":"Middleware JBOSS","Environments":"Administration","Component":"A11992437"},{"ComponentName":"JBOSS ON SVSVACMECRMTAPP01","state":"ok","Service Categories":"APPLICATION","Service Units":"MIS.INT.HU.ALP.LIN.APP","Systemparts":"Middleware JBOSS","Environments":"Preprod","Component":"A11992405"},{"ComponentName":"JBOSS ON SVSVACMECRMTAPP02","state":"ok","Service Categories":"APPLICATION","Service Units":"MIS.INT.HU.ALP.LIN.APP","Systemparts":"Middleware JBOSS","Environments":"Preprod","Component":"A11992434"},{"ComponentName":"ACME HFIX JBOSS_CROSS ON SVSVACMEACMEHAPP01","state":"ok","Service Categories":"APPLICATION","Service Units":"MIS.INT.HU.ALP.LIN.APP","Systemparts":"Middleware JBOSS","Environments":"Release Test","Component":"A11854302"},{"ComponentName":"ACME PROD JBOSS_CROSS ON SVSVACMEACMEPAPP01","state":"ok","Service Categories":"APPLICATION","Service Units":"MIS.INT.HU.ALP.LIN.APP","Systemparts":"Middleware JBOSS","Environments":"Production","Component":"A11854439"},{"ComponentName":"ACME PROD JBOSS_CROSS ON SVSVACMEACMEPAPP02","state":"ok","Service Categories":"APPLICATION","Service Units":"MIS.INT.HU.ALP.LIN.APP","Systemparts":"Middleware JBOSS","Environments":"Production","Component":"A11960323"},{"ComponentName":"ACME HFIX JBOSS_LF ON SVSVACMEACMEHAPP01","state":"ok","Service Categories":"APPLICATION","Service Units":"MIS.INT.HU.ALP.LIN.APP","Systemparts":"Middleware JBOSS","Environments":"Release Test","Component":"A11854275"}]}
